jsontool.py
jsontool-0.2.1.dist-info/DESCRIPTION.rst
jsontool-0.2.1.dist-info/entry_points.txt
jsontool-0.2.1.dist-info/METADATA
jsontool-0.2.1.dist-info/metadata.json
jsontool-0.2.1.dist-info/RECORD
jsontool-0.2.1.dist-info/top_level.txt
jsontool-0.2.1.dist-info/WHEEL
