Metadata-Version: 1.1
Name: jsontool
Version: 0.2.1
Summary: `jsontool` is utility to fighting with JSON files using CLI
Home-page: http://github.com/mysz/jsontool/
Author: Marcin Sztolcman
Author-email: marcin@urzenia.net
License: MIT
Keywords: json processing grep sort
Platform: UNKNOWN
Classifier: Development Status :: 3 - Alpha
Classifier: Environment :: Console
Classifier: Intended Audience :: Developers
Classifier: Intended Audience :: Other Audience
Classifier: Intended Audience :: System Administrators
Classifier: License :: OSI Approved :: MIT License
Classifier: Topic :: Utilities
Classifier: Programming Language :: Python :: 2
Classifier: Programming Language :: Python :: 2.6
Classifier: Programming Language :: Python :: 2.7
